{"_id":{"$oid":"5c374cb4af97084a54dd051a"},"employeeId":"759585","firstName":"Oscar","lastName":"Collins","department":{"$oid":"5c374cb3af97084a54dd0519"},"__v":0}
{"_id":{"$oid":"5c374cb4af97084a54dd051b"},"employeeId":"302495","firstName":"Napoleon","lastName":"Cartwright","department":{"$oid":"5c374cb3af97084a54dd0516"},"__v":0}
{"_id":{"$oid":"5c374cb4af97084a54dd051c"},"employeeId":"534006","firstName":"Lane","lastName":"Kessler","department":{"$oid":"5c374cb3af97084a54dd0515"},"__v":0}
{"_id":{"$oid":"5c374cb4af97084a54dd051d"},"employeeId":"341905","firstName":"Juliet","lastName":"McGlynn","department":{"$oid":"5c374cb3af97084a54dd0515"},"__v":0}
{"_id":{"$oid":"5c374cb4af97084a54dd051e"},"employeeId":"294020","firstName":"Gladys","lastName":"White","department":{"$oid":"5c374cb3af97084a54dd0518"},"__v":0}
{"_id":{"$oid":"5c374cb4af97084a54dd051f"},"employeeId":"259413","firstName":"Camren","lastName":"Johnson","department":{"$oid":"5c374cb3af97084a54dd0519"},"__v":0}
{"_id":{"$oid":"5c374cb4af97084a54dd0520"},"employeeId":"307610","firstName":"Stephen","lastName":"Hettinger","department":{"$oid":"5c374cb3af97084a54dd0518"},"__v":0}
{"_id":{"$oid":"5c374cb4af97084a54dd0521"},"employeeId":"470296","firstName":"August","lastName":"Gleichner","department":{"$oid":"5c374cb3af97084a54dd0516"},"__v":0}
{"_id":{"$oid":"5c374cb4af97084a54dd0522"},"employeeId":"109705","firstName":"Lukas","lastName":"Buckridge","department":{"$oid":"5c374cb3af97084a54dd0517"},"__v":0}
{"_id":{"$oid":"5c374cb4af97084a54dd0523"},"employeeId":"449375","firstName":"Rafaela","lastName":"Satterfield","department":{"$oid":"5c374cb3af97084a54dd0517"},"__v":0}
{"_id":{"$oid":"5c374cb4af97084a54dd0524"},"employeeId":"426980","firstName":"Michel","lastName":"Hartmann","department":{"$oid":"5c374cb3af97084a54dd0519"},"__v":0}
{"_id":{"$oid":"5c374cb4af97084a54dd0525"},"employeeId":"192653","firstName":"Robyn","lastName":"McKenzie","department":{"$oid":"5c374cb3af97084a54dd0517"},"__v":0}
{"_id":{"$oid":"5c374cb4af97084a54dd0526"},"employeeId":"433279","firstName":"Chaz","lastName":"Will","department":{"$oid":"5c374cb3af97084a54dd0516"},"__v":0}
{"_id":{"$oid":"5c374cb4af97084a54dd0527"},"employeeId":"661893","firstName":"Adah","lastName":"Heaney","department":{"$oid":"5c374cb3af97084a54dd0515"},"__v":0}
{"_id":{"$oid":"5c374cb4af97084a54dd0528"},"employeeId":"524074","firstName":"Bulah","lastName":"Tremblay","department":{"$oid":"5c374cb3af97084a54dd0515"},"__v":0}
